dogsbody/__init__.py
dogsbody/__main__.py
dogsbody/bundle.py
dogsbody/daemon.py
dogsbody/dog.py
dogsbody/runtime.py
dogsbody/utils.py
dogsbody-0.1.7.dist-info/LICENSE
dogsbody-0.1.7.dist-info/METADATA
dogsbody-0.1.7.dist-info/WHEEL
dogsbody-0.1.7.dist-info/entry_points.txt
dogsbody-0.1.7.dist-info/top_level.txt
dogsbody-0.1.7.dist-info/RECORD
