Metadata-Version: 2.1
Name: dogsbody
Version: 0.1.7
Summary: A tool to create and execute a "special setup"/"data file".
Home-page: https://github.com/axju/dogsbody
Author: axju
Author-email: moin@axju.de
License: MIT
Classifier: Intended Audience :: Developers
Classifier: Operating System :: OS Independent
Classifier: Programming Language :: Python
Classifier: Programming Language :: Python :: 3.6
Classifier: Programming Language :: Python :: 3.7
Classifier: Programming Language :: Python :: 3.8
License-File: LICENSE
Requires-Dist: dynaconf
Requires-Dist: importlib-metadata ; python_version < "3.8.0"
